{"number_of_lines": 667, "number_of_things": 172, "number_of_sectors": 100, "number_of_subsectors": 373, "number_of_vertices": 671, "x_max": 1792, "y_max": 2560, "x_min": -2112, "y_min": -1744, "height": 4305, "width": 3905, "aspect_ratio": 1.1024327784891166, "floor_height_max": 125.0, "floor_height_min": -100.0, "floor_height_avg": 19.28, "ceiling_height_max": 200.0, "ceiling_height_min": -10.0, "ceiling_height_avg": 111.31, "room_height_max": 300.0, "room_height_min": 0.0, "room_height_avg": 92.03, "sector_area_max": 1191936.0, "sector_area_min": 0.0, "sector_area_avg": 69056.0, "lines_per_sector_max": 63.0, "lines_per_sector_min": 4.0, "lines_per_sector_avg": 9.2, "sector_aspect_ratio_max": 11.830769230769231, "sector_aspect_ratio_min": 1.0, "sector_aspect_ratio_avg": 2.776297857269445, "floors": 2, "level_area": 6070, "floors_area_mean": 3035.0, "floors_area_min": 648, "floors_area_max": 5422, "floors_area_std": 2387.0, "level_bbox_area": 16605, "level_convex_area": 12219, "floors_convex_area_mean": 6433.5, "floors_convex_area_min": 648, "floors_convex_area_max": 12219, "floors_convex_area_std": 5785.5, "level_eccentricity": 0.6849957060651813, "floors_eccentricity_mean": 0.7748579778741091, "floors_eccentricity_min": 0.6833562437468174, "floors_eccentricity_max": 0.866359712001401, "floors_eccentricity_std": 0.09150173412729184, "level_equivalent_diameter": 87.9122519137261, "floors_equivalent_diameter_mean": 55.90558831312459, "floors_equivalent_diameter_min": 28.723844188903154, "floors_equivalent_diameter_max": 83.08733243734602, "floors_equivalent_diameter_std": 27.181744124221435, "level_euler_number": -3, "floors_euler_number_mean": -1.5, "floors_euler_number_min": -4, "floors_euler_number_max": 1, "floors_euler_number_std": 2.5, "level_extent": 0.36555254441433305, "floors_extent_mean": 0.6632640770852153, "floors_extent_min": 0.3265281541704306, "floors_extent_max": 1.0, "floors_extent_std": 0.3367359229147847, "level_filled_area": 9418, "floors_filled_area_mean": 5033.0, "floors_filled_area_min": 648, "floors_filled_area_max": 9418, "floors_filled_area_std": 4385.0, "level_major_axis_length": 152.0745994406507, "floors_major_axis_length_mean": 100.89426873492864, "floors_major_axis_length_min": 41.55317877932646, "floors_major_axis_length_max": 160.23535869053083, "floors_major_axis_length_std": 59.341089955602186, "level_minor_axis_length": 110.79350900666822, "floors_minor_axis_length_mean": 68.86897838089682, "floors_minor_axis_length_min": 20.752509888364507, "floors_minor_axis_length_max": 116.98544687342914, "floors_minor_axis_length_std": 48.11646849253231, "level_orientation": -1.4842677416479462, "floors_orientation_mean": 0.043555157669121325, "floors_orientation_min": -1.483686011456654, "floors_orientation_max": 1.5707963267948966, "floors_orientation_std": 1.5272411691257752, "level_perimeter": 1206.0426765808693, "floors_perimeter_mean": 603.0213382904346, "floors_perimeter_min": 104.0, "floors_perimeter_max": 1102.0426765808693, "floors_perimeter_std": 499.02133829043464, "level_solidity": 0.49676732956870445, "floors_solidity_mean": 0.7218675832719536, "floors_solidity_min": 0.44373516654390704, "floors_solidity_max": 1.0, "floors_solidity_std": 0.27813241672804645, "level_hu_moment_0": 0.36451694226776177, "level_hu_moment_1": 0.01248420161739261, "level_hu_moment_2": 0.0006958706768184252, "level_hu_moment_3": 8.185451658018167e-05, "level_hu_moment_4": -3.2008625802351356e-09, "level_hu_moment_5": -2.092997887248988e-06, "level_hu_moment_6": -1.9271656839267698e-08, "level_centroid_x": 67.94695222405272, "level_centroid_y": 66.54085667215816, "number_of_artifacts": 73, "number_of_powerups": 17, "number_of_weapons": 21, "number_of_ammunitions": 22, "number_of_keys": 0, "number_of_monsters": 0, "number_of_obstacles": 9, "number_of_decorations": 0, "walkable_area": 4566, "walkable_percentage": 0.7522240527182866, "start_location_x_px": 25, "start_location_y_px": 111, "artifacts_per_walkable_area": 0.01598773543583005, "powerups_per_walkable_area": 0.0037231712658782304, "weapons_per_walkable_area": 0.0045992115637319315, "ammunitions_per_walkable_area": 0.004818221638195357, "keys_per_walkable_area": 0.0, "monsters_per_walkable_area": 0.0, "obstacles_per_walkable_area": 0.0019710906701708277, "decorations_per_walkable_area": 0.0, "nodes": 92, "avg-path-length": 8.320028011204482, "diameter-mean": 18.5, "art-points": 16, "assortativity-mean": -0.2900834105653398, "betw-cen": NaN, "closn-cen": NaN, "distmap-max": 19.0, "distmap-mean": -Infinity, "distmap-var": 0.0, "distmap-skew": 0, "distmap-kurt": 0.0, "distmap-Q1": 0.03911273911273911, "distmap-Q2": 0.12091982091982093, "distmap-Q3": 0.1907203907203906, "path_wallmap": "DWANGO5_MAP23_wallmap.png", "path_heightmap": "DWANGO5_MAP23_heightmap.png", "path_triggermap": "DWANGO5_MAP23_triggermap.png", "path_thingsmap": "DWANGO5_MAP23_thingsmap.png", "path_floormap": "DWANGO5_MAP23_floormap.png", "path_roommap": "DWANGO5_MAP23_roommap.png", "slot": "MAP23", "path_json": "DWANGO5_MAP23.json"}