{"number_of_lines": 497, "number_of_things": 62, "number_of_sectors": 120, "number_of_subsectors": 240, "number_of_vertices": 399, "x_max": -768, "y_max": 4480, "x_min": -3584, "y_min": 2240, "height": 2241, "width": 2817, "aspect_ratio": 1.2570281124497993, "floor_height_max": 256.0, "floor_height_min": 0.0, "floor_height_avg": 61.2, "ceiling_height_max": 336.0, "ceiling_height_min": 0.0, "ceiling_height_avg": 258.3333333333333, "room_height_max": 336.0, "room_height_min": 0.0, "room_height_avg": 197.13333333333333, "sector_area_max": 588288.0, "sector_area_min": 512.0, "sector_area_avg": 35389.86666666667, "lines_per_sector_max": 52.0, "lines_per_sector_min": 3.0, "lines_per_sector_avg": 6.258333333333334, "sector_aspect_ratio_max": 21.363636363636363, "sector_aspect_ratio_min": 1.0, "sector_aspect_ratio_avg": 3.9606454258863795, "floors": 1, "level_area": 4378, "floors_area_mean": 4378.0, "floors_area_min": 4378, "floors_area_max": 4378, "floors_area_std": 0.0, "level_bbox_area": 6319, "level_convex_area": 5183, "floors_convex_area_mean": 5183.0, "floors_convex_area_min": 5183, "floors_convex_area_max": 5183, "floors_convex_area_std": 0.0, "level_eccentricity": 0.5434428748217232, "floors_eccentricity_mean": 0.5434428748217232, "floors_eccentricity_min": 0.5434428748217232, "floors_eccentricity_max": 0.5434428748217232, "floors_eccentricity_std": 0.0, "level_equivalent_diameter": 74.66085136703533, "floors_equivalent_diameter_mean": 74.66085136703533, "floors_equivalent_diameter_min": 74.66085136703533, "floors_equivalent_diameter_max": 74.66085136703533, "floors_equivalent_diameter_std": 0.0, "level_euler_number": -5, "floors_euler_number_mean": -5.0, "floors_euler_number_min": -5, "floors_euler_number_max": -5, "floors_euler_number_std": 0.0, "level_extent": 0.6928311441683811, "floors_extent_mean": 0.6928311441683811, "floors_extent_min": 0.6928311441683811, "floors_extent_max": 0.6928311441683811, "floors_extent_std": 0.0, "level_filled_area": 4462, "floors_filled_area_mean": 4462.0, "floors_filled_area_min": 4462, "floors_filled_area_max": 4462, "floors_filled_area_std": 0.0, "level_major_axis_length": 86.9478013774145, "floors_major_axis_length_mean": 86.9478013774145, "floors_major_axis_length_min": 86.9478013774145, "floors_major_axis_length_max": 86.9478013774145, "floors_major_axis_length_std": 0.0, "level_minor_axis_length": 72.9879972754852, "floors_minor_axis_length_mean": 72.9879972754852, "floors_minor_axis_length_min": 72.9879972754852, "floors_minor_axis_length_max": 72.9879972754852, "floors_minor_axis_length_std": 0.0, "level_orientation": 0.3179839805686209, "floors_orientation_mean": 0.3179839805686209, "floors_orientation_min": 0.3179839805686209, "floors_orientation_max": 0.3179839805686209, "floors_orientation_std": 0.0, "level_perimeter": 492.8528137423857, "floors_perimeter_mean": 492.8528137423857, "floors_perimeter_min": 492.8528137423857, "floors_perimeter_max": 492.8528137423857, "floors_perimeter_std": 0.0, "level_solidity": 0.844684545629944, "floors_solidity_mean": 0.844684545629944, "floors_solidity_min": 0.844684545629944, "floors_solidity_max": 0.844684545629944, "floors_solidity_std": 0.0, "level_hu_moment_0": 0.18397624358514963, "level_hu_moment_1": 0.0010159177181052058, "level_hu_moment_2": 0.0011052378446375095, "level_hu_moment_3": 7.785990861248339e-05, "level_hu_moment_4": 7.665843519506378e-09, "level_hu_moment_5": 1.2563740672983563e-06, "level_hu_moment_6": -2.151526689876646e-08, "level_centroid_x": 47.412973960712655, "level_centroid_y": 32.75582457743262, "number_of_artifacts": 0, "number_of_powerups": 1, "number_of_weapons": 14, "number_of_ammunitions": 0, "number_of_keys": 0, "number_of_monsters": 0, "number_of_obstacles": 18, "number_of_decorations": 11, "walkable_area": 3777, "walkable_percentage": 0.8627227044312471, "start_location_x_px": 1, "start_location_y_px": 1, "artifacts_per_walkable_area": 0.0, "powerups_per_walkable_area": 0.00026476039184537993, "weapons_per_walkable_area": 0.003706645485835319, "ammunitions_per_walkable_area": 0.0, "keys_per_walkable_area": 0.0, "monsters_per_walkable_area": 0.0, "obstacles_per_walkable_area": 0.004765687053216839, "decorations_per_walkable_area": 0.0029123643102991793, "nodes": 16, "avg-path-length": 2.841666666666667, "diameter-mean": 6.0, "art-points": 2, "assortativity-mean": -0.219547775346463, "betw-cen": NaN, "closn-cen": NaN, "distmap-max": 22.02271554554524, "distmap-mean": -Infinity, "distmap-var": 0.0, "distmap-skew": 0, "distmap-kurt": 0.0, "distmap-Q1": 0.014285714285714287, "distmap-Q2": 0.08095238095238096, "distmap-Q3": 0.1928571428571429, "path_wallmap": "DWANGO20_MAP04_wallmap.png", "path_heightmap": "DWANGO20_MAP04_heightmap.png", "path_triggermap": "DWANGO20_MAP04_triggermap.png", "path_thingsmap": "DWANGO20_MAP04_thingsmap.png", "path_floormap": "DWANGO20_MAP04_floormap.png", "path_roommap": "DWANGO20_MAP04_roommap.png", "slot": "MAP04", "path_json": "DWANGO20_MAP04.json"}